anthpy/__init__.py
anthpy/strings.py
anthpy/version.py
anthpy/tools/__init__.py
anthpy-0.1.data/data/share/anthpy/README.rst
anthpy-0.1.dist-info/METADATA
anthpy-0.1.dist-info/RECORD
anthpy-0.1.dist-info/WHEEL
anthpy-0.1.dist-info/entry_points.txt
anthpy-0.1.dist-info/top_level.txt
