Metadata-Version: 2.1
Name: anthpy
Version: 0.1
Summary: Anthony's python utils
Home-page: https://github.com/aagnone3/anthpy
Author: Anthony Agnone
Author-email: anthonyagnone@gmail.com
License: UNKNOWN
Platform: UNKNOWN
Classifier: Development Status :: 3 - Alpha
Classifier: Programming Language :: Python :: 3
Classifier: Topic :: Scientific/Engineering
Requires-Dist: pandas
Requires-Dist: numpy
